{"cameraMode":{"drawMode":0,"name":"Shaded","section":"Shading Mode"},"sceneLighting":false,"audioPlay":false,"sceneViewState":{"m_AlwaysRefresh":false,"showFog":true,"showSkybox":false,"showFlares":true,"showImageEffects":true,"showParticleSystems":true,"showVisualEffectGraphs":true,"m_FxEnabled":true},"in2DMode":false,"pivot":{"x":-27.220714569091798,"y":6.4837327003479,"z":-8.19954776763916},"rotation":{"x":0.273600310087204,"y":-0.26097428798675539,"z":0.07741593569517136,"w":0.9225545525550842},"size":1.1262853145599366,"orthographic":false}